[{
  "_id": {
    "$oid": "656349a137a2a92a2d57dd45"
  },
  "nombre": "Sofia",
  "apellido": "Rozo",
  "email": "as.rozo",
  "telefono": "3124744532",
  "documento": "1032876365",
  "tipo_documento": "CC"
},
{
  "_id": {
    "$oid": "656cbd042af4696abe21e04b"
  },
  "nombre": "Juanmi",
  "apellido": "Rozo",
  "email": "829292",
  "telefono": "22222222",
  "documento": "j.miguel@gmail",
  "tipo_documento": "TI",
  "_class": "com.example.demo.modelo.Clientes"
},
{
  "_id": {
    "$oid": "656cbee5c4624b51b135ffe0"
  },
  "nombre": "Juanmi",
  "apellido": "Rozo",
  "email": "829292",
  "telefono": "22222222",
  "documento": "j.miguel@gmail",
  "tipo_documento": "TI",
  "_class": "com.example.demo.modelo.Clientes"
},
{
  "_id": {
    "$oid": "656cd84a9fc2471c5e9e3fe8"
  },
  "nombre": "Juanmi",
  "apellido": "Rozo",
  "email": "829292",
  "telefono": "22222222",
  "documento": "j.miguel@gmail",
  "tipo_documento": "TI",
  "_class": "com.example.demo.modelo.Clientes"
}]